scripts/__init__.py
scripts/action.py
scripts/assign_bson_type.py
scripts/db_create.py
scripts/db_destroy.py
scripts/delete.py
scripts/entry.py
scripts/file_add.py
scripts/file_delete.py
scripts/file_dl.py
scripts/find.py
scripts/item_delete.py
scripts/pullout.py
scripts/structure_convert.py
scripts/update.py
venv/bin/jp.py
edman_cli-2025.1.31.dist-info/LICENSE.txt
edman_cli-2025.1.31.dist-info/METADATA
edman_cli-2025.1.31.dist-info/WHEEL
edman_cli-2025.1.31.dist-info/entry_points.txt
edman_cli-2025.1.31.dist-info/top_level.txt
edman_cli-2025.1.31.dist-info/RECORD
