Metadata-Version: 2.2
Name: edman_cli
Version: 2025.1.31
Summary: Sub-package of edman for cli applications and scripts.
Author-email: Masaki Ohno <masakio@post.kek.jp>
License: MIT License
Project-URL: repository, https://github.com/ryde/edman_cli
Classifier: Programming Language :: Python :: 3
Classifier: Programming Language :: Python :: 3.12
Classifier: License :: OSI Approved :: MIT License
Classifier: Topic :: Database :: Front-Ends
Requires-Python: >=3.12
License-File: LICENSE.txt
Requires-Dist: pymongo~=4.11
Requires-Dist: python-dateutil~=2.9.0.post0
Requires-Dist: jmespath~=1.0.1
Requires-Dist: edman~=2025.1.31
